sense_table/__init__.py
sense_table/app.py
sense_table/cli.py
sense_table/exceptions.py
sense_table/handlers/__init__.py
sense_table/handlers/fs.py
sense_table/handlers/pages.py
sense_table/handlers/query.py
sense_table/handlers/s3.py
sense_table/statics/404.html
sense_table/statics/FolderBrowser.html
sense_table/statics/FolderBrowser.txt
sense_table/statics/Table.html
sense_table/statics/Table.txt
sense_table/statics/favicon.ico
sense_table/statics/index.html
sense_table/statics/index.txt
sense_table/statics/test.html
sense_table/statics/test.txt
sense_table/statics/_next/static/3ouYabw1s_qSfV-WhqOlD/_buildManifest.js
sense_table/statics/_next/static/3ouYabw1s_qSfV-WhqOlD/_ssgManifest.js
sense_table/statics/_next/static/chunks/06d028f4-d7f236a86cd66aa4.js
sense_table/statics/_next/static/chunks/1191.42e822a828c46114.js
sense_table/statics/_next/static/chunks/1258.154e33eb48073a5c.js
sense_table/statics/_next/static/chunks/139-eb7bb73d658a0de2.js
sense_table/statics/_next/static/chunks/1573.ed711f5c5d32973f.js
sense_table/statics/_next/static/chunks/191d07e0-df4a879656760d37.js
sense_table/statics/_next/static/chunks/2289.8ba0abf0504e3a17.js
sense_table/statics/_next/static/chunks/232.0ed163cb8bcb914d.js
sense_table/statics/_next/static/chunks/2513.2c8bea53b3bddb6a.js
sense_table/statics/_next/static/chunks/2561-7cb822b62e16f8ce.js
sense_table/statics/_next/static/chunks/2745.9d40e0704e88bf2d.js
sense_table/statics/_next/static/chunks/2854.4f95d62acf5ad6a9.js
sense_table/statics/_next/static/chunks/3076.058deef50463164a.js
sense_table/statics/_next/static/chunks/3405.7cd385b68774f9ff.js
sense_table/statics/_next/static/chunks/3452-31e84d94866fa0bc.js
sense_table/statics/_next/static/chunks/3570.e5767b52080454d9.js
sense_table/statics/_next/static/chunks/3714.9dddd781af554648.js
sense_table/statics/_next/static/chunks/3736.9ef4cc5e0e96a68c.js
sense_table/statics/_next/static/chunks/3882.76f5098b338333d0.js
sense_table-0.0.2rc5.dist-info/METADATA
sense_table-0.0.2rc5.dist-info/WHEEL
sense_table-0.0.2rc5.dist-info/entry_points.txt
sense_table-0.0.2rc5.dist-info/top_level.txt
sense_table-0.0.2rc5.dist-info/RECORD
